inkplot/__init__.py
inkplot/cli.py
inkplot/exceptions.py
inkplot/exporter.py
inkplot/layered_svg.py
inkplot/pages.py
inkplot/svg_locator.py
inkplot-0.2.1.dist-info/AUTHORS.md
inkplot-0.2.1.dist-info/LICENSE
inkplot-0.2.1.dist-info/METADATA
inkplot-0.2.1.dist-info/WHEEL
inkplot-0.2.1.dist-info/entry_points.txt
inkplot-0.2.1.dist-info/top_level.txt
inkplot-0.2.1.dist-info/RECORD
