Metadata-Version: 2.1
Name: inkplot
Version: 0.2.1
Summary: a simple presentation utility that turns inkscape SVGs into images and multi-page pdfs with configurable layer visibility and zoom definitions
Author-email: Fred McDavid <fred@frameworklabs.us>
License: License :: OSI Approved :: GNU General Public License v3 (GPLv3)
Project-URL: Homepage, https://gitlab.com/frameworklabs/inkplot/
Keywords: inkscape,pdf
Classifier: Development Status :: 3 - Alpha
Classifier: Programming Language :: Python :: 3
Classifier: Intended Audience :: End Users/Desktop
Classifier: Topic :: Multimedia :: Graphics
Classifier: Topic :: Multimedia :: Graphics :: Presentation
Classifier: Topic :: Scientific/Engineering
Classifier: Topic :: Utilities
Requires-Python: >=3.6
License-File: LICENSE
License-File: AUTHORS.md
Requires-Dist: click
Requires-Dist: PyYAML
Requires-Dist: PyPDF2
